clouder/__init__.py
clouder/__main__.py
clouder/_version.py
clouder/application.py
clouder/serverapplication.py
clouder/apps/__init__.py
clouder/apps/config.py
clouder/apps/keypair.py
clouder/apps/kubernetes.py
clouder/apps/shell.py
clouder/apps/up.py
clouder/apps/virtual_machine.py
clouder/cloud/__init__.py
clouder/cloud/ovh/__init__.py
clouder/cloud/ovh/create_database_mysql.py
clouder/cloud/ovh/create_kubernetes.py
clouder/cloud/ovh/get_apps.py
clouder/cloud/ovh/get_authorized_apps.py
clouder/cloud/ovh/get_bills.py
clouder/cloud/ovh/get_consumer_key.py
clouder/cloud/ovh/get_databases_mysql.py
clouder/cloud/ovh/get_services.py
clouder/cloud/ovh/get_services_expiring.py
clouder/cloud/ovh/me.py
clouder/cloud/ovh/api/cloud.json
clouder/resources/k8s/README.md
clouder/resources/k8s/tf_k8s_1/README.md
clouder/resources/k8s/tf_k8s_1/outputs.tf
clouder/resources/k8s/tf_k8s_1/provider.tf
clouder/resources/k8s/tf_k8s_1/resources.tf
clouder/resources/k8s/tf_k8s_2/README.md
clouder/resources/k8s/tf_k8s_2/outputs.tf
clouder/resources/k8s/tf_k8s_2/provider.tf
clouder/resources/k8s/tf_k8s_2/resources.tf
clouder/resources/k8s/tf_k8s_3/README.md
clouder/resources/k8s/tf_k8s_3/outputs.tf
clouder/resources/k8s/tf_k8s_3/provider.tf
clouder/resources/k8s/tf_k8s_3/resources.tf
clouder/resources/kubeadm/Makefile
clouder/resources/kubeadm/README.md
clouder/resources/kubeadm/outputs.tf
clouder/resources/kubeadm/provider.tf
clouder/resources/kubeadm/resources.tf
clouder/resources/kubeadm/variables.tf
clouder/resources/kubeadm/_resources/gpu-centos-base.sh
clouder/resources/kubeadm/_resources/gpu-centos-docker.sh
clouder/resources/kubeadm/_resources/gpu-centos-kubernetes.sh
clouder/resources/kubeadm/_resources/gpu-ubuntu-base.sh
clouder/resources/kubeadm/_resources/kubeadm-common_centos_7.sh
clouder/resources/kubeadm/_resources/kubeadm-common_ubuntu_20.04.sh
clouder/resources/kubeadm/_resources/kubeadm-master.sh
clouder/resources/kubeadm/_resources/kubeadm-master.yaml
clouder-0.0.5.dist-info/METADATA
clouder-0.0.5.dist-info/WHEEL
clouder-0.0.5.dist-info/entry_points.txt
clouder-0.0.5.dist-info/licenses/LICENSE
clouder-0.0.5.dist-info/RECORD
