Metadata-Version: 2.1
Name: clouder
Version: 0.0.5
Summary: ☁️ Clouder.
Project-URL: Homepage, https://github.com/datalayer/clouder
Project-URL: Bug Tracker, https://github.com/datalayer/clouder/issues
Project-URL: Repository, https://github.com/datalayer/clouder.git
Author-email: Datalayer <info@datalayer.io>
License: BSD 3-Clause License
License-File: LICENSE
Classifier: Framework :: Jupyter
Classifier: Framework :: Jupyter :: JupyterLab
Classifier: Framework :: Jupyter :: JupyterLab :: 4
Classifier: Framework :: Jupyter :: JupyterLab :: Extensions
Classifier: Framework :: Jupyter :: JupyterLab :: Extensions :: Prebuilt
Classifier: Intended Audience :: Developers
Classifier: Intended Audience :: Science/Research
Classifier: Intended Audience :: System Administrators
Classifier: License :: OSI Approved :: BSD License
Classifier: Programming Language :: Python
Classifier: Programming Language :: Python :: 3
Classifier: Programming Language :: Python :: 3.11
Requires-Python: >=3.11
Requires-Dist: avionix
Requires-Dist: boto3
Requires-Dist: datalayer
Requires-Dist: kopf
Requires-Dist: ovh
Provides-Extra: test
Requires-Dist: coverage; extra == 'test'
Requires-Dist: pytest; extra == 'test'
Requires-Dist: pytest-asyncio; extra == 'test'
Requires-Dist: pytest-cov; extra == 'test'
Requires-Dist: pytest-jupyter; extra == 'test'
Requires-Dist: pytest-tornasync; extra == 'test'
